{
    "ASGBD": {
        "id": 26,
        "name": "Administración de sistemas gestores de base de datos",
        "teacher": "Rafael Chacón",
        "teacher_mail": "rafa.chacon.almeda@digitechfp.com",
        "units": {
            "ASGBD-1": {
                "folder": 16661,
                "folder_number": 1,
                "name": "Unidad 1 y 2. Instalación de un sistema gestor de bases de datos",
                "link": "https://drive.google.com/file/d/1BiZfxIgfzv4A-dqeRcWsG8g_2y-p9H3d/view?usp=sharing"
            },
            "ASGBD-2": {
                "folder": 16662,
                "folder_number": 1,
                "name": "Unidad 3.1. Acceso a la información DCL",
                "link": "https://drive.google.com/file/d/1YEyzj_AUDTgnzLjVXsIEx59EyRQI6NOs/view?usp=sharing"
            },
            "ASGBD-3": {
                "folder": 16663,
                "folder_number": 1,
                "name": "Unidad 3.2. Acceso a la información: vistas",
                "link": "https://drive.google.com/file/d/1qs2Vwn_2myZKCq0eRHpnTWuIC6r5jv63/view?usp=sharing"
            },
            "ASGBD-4": {
                "folder": 16664,
                "folder_number": 1,
                "name": "Unidad 4.1. Programación de bases de datos: conceptos iniciales",
                "link": "https://drive.google.com/file/d/1U9VYyViqzxZ_xeuQNCf28RKg5uVUKe1f/view?usp=sharing"
            },
            "ASGBD-5": {
                "folder": 16665,
                "folder_number": 1,
                "name": "Unidad 4.2. Herramientas de programación de bases de datos",
                "link": "https://drive.google.com/file/d/19slb9KtPWq5B6AA8Tk7JmqL0K1bKp_N4/view?usp=sharing"
            }
        },
        "resources": {
            "CH_M-1": {       
                "name": "Chuleta Manuel T1",
                "file": "CHULETA BASE DE DATOS 2.pdf",
                "link": "https://drive.google.com/file/d/1j6zoRejGQ_Yv5nWkws4OrDRj1TlhruNX/view?usp=drive_link"
            }},
        "tasks": {
            "8735": {
                "type": "Obligatoria",
                "start": "07-10-2025 18:30",
                "end": "22-10-2025 23:59",
                "name": "Tarea 1 - Instalación de un sistema gestor de bases de datos OBLIGATORIA"
            },
            "4475": {
                "type": "Obligatoria",
                "start": "23-10-2025 00:00",
                "end": "23-11-2025 23:59",
                "name": "Tarea 2 - Acceso a la información DCL. OBLIGATORIA"
            },
            "17409": {
                "type": "Complementaria",
                "start": "23-10-2025 10:26",
                "end": "16-11-2025 23:59",
                "name": "Tarea 01-02 Usuarios en BD de pedidos"
            },
            "9886": {
                "type": "Complementaria",
                "start": "23-10-2025 10:31",
                "end": "16-11-2025 23:59",
                "name": "Tarea 01-03 Control de la BD de pruebas"
            },
            "1931": {
                "type": "Obligatoria",
                "start": "05-15-2025 12:32",
                "end": "30-11-2025 23:59",
                "name": "Tarea 3- Acceso a la información: vistas. OBLIGATORIA"
            },
            "3123": {
                "type": "Obligatoria",
                "start": "26-01-2026 12:32",
                "end": "15-02-2026 23:59",
                "name": "Tarea 4 - Programación de bases de datos: conceptos iniciales (RA5). OBLIGATORIA"
            },
            "3452": {
                "type": "Obligatoria",
                "start": "26-01-2026 12:32",
                "end": "15-02-2026 23:59",
                "name": "Tarea 5 - Programación de bases de datos: conceptos iniciales (RA5). OBLIGATORIA"
            },
            "3454": {
                "type": "Complementaria",
                "start": "26-01-2026 12:32",
                "end": "15-02-2026 23:59",
                "name": "Tarea 03-02 Procedimiento de calcular cuadrados"
            },
            "3453": {
                "type": "Complementaria",
                "start": "26-01-2026 12:32",
                "end": "15-02-2026 23:59",
                "name": "Tarea 03-03 Procedimientos en SAKILA"
            },
            "3451": {
                "type": "Complementaria",
                "start": "26-01-2026 12:32",
                "end": "22-02-2026 23:59",
                "name": "Tarea 03-04 Procedimientos entrada y salida iniciales (Pedidos)"
            },
            "8840": {
                "type": "Complementaria",
                "start": "13-02-2026 12:32",
                "end": "01-03-2026 23:59",
                "name": "Tarea 03-05 Suma de pagos en jardinería (funciones)"
            },
            "8841": {
                "type": "Complementaria",
                "start": "13-02-2026 12:32",
                "end": "08-03-2026 23:59",
                "name": "Tarea 03-06 Importe de un pedido"
            },
            "8844": {
                "type": "Complementaria",
                "start": "13-02-2026 12:32",
                "end": "08-03-2026 23:59",
                "name": "Tarea 03-07 BD de instituto (funciones)"
            }
        },
        "tests": {
            "17218": {
                "type": "Cuestionario",
                "start": "",
                "end": "",
                "name": "Cuestionario - Instalación SGBD"
            },
            "17219": {
                "type": "Cuestionario",
                "start": "",
                "end": "",
                "name": "Cuestionario - Acceso a la información (DCL y vistas)"
            },
            "ASGBD-DICIEMBRE": {
                "type": "Cuestionario",
                "start": "",
                "end": "",
                "name": "AUTOEVALUACIÓN DICIEMBRE"
            },
            "ASGBD-ENERO": {
                "type": "Cuestionario",
                "start": "",
                "end": "",
                "name": "EXAMEN ENERO"
            },
            "17220": {
                "type": "Cuestionario",
                "start": "",
                "end": "",
                "name": "Cuestionario - Programación en bases de datos"
            }
        },
        "notes": {
            "ASGBD-doc": {
                "name": "Apuntes ASGBD (doc)",
                "link": "https://docs.google.com/document/d/1VFDbbRa5pZDAaUlfkLULicYsuIojtwhCQMkDdL4nBkc/edit?usp=sharing"
            }
        }
    },
    "ASO": {
        "id": 20,
        "name": "Administración de sistemas operativos",
        "teacher": "Carlos Quintana",
        "teacher_mail": "cquintana@digitechfp.com",
        "units": {
            "ASO-0": {
                "folder": 18359,
                "folder_number": 1,
                "name": "Administración de servicio de directorio (Cisco)",
                "link": "https://drive.google.com/file/d/1Kw6Zbmpg7bTTTDhc3yN98rVPb5oKftiX/view?usp=sharing"
            }
        },
        "resources": {},
        "tasks": {
            "34766": {
                "type": "Complementaria",
                "start": "23-10-2025 00:00",
                "end": "29-05-2026 23:00",
                "name": "Actividad Complementaria 4"
            },
            "23366": {
                "type": "Obligatoria",
                "start": "30-10-2025 00:00",
                "end": "30-11-2025 23:59",
                "name": "Tarea Usuarios y Grupos con Ubuntu (Tarea Obligatoria)"
            },
            "35973": {
                "type": "Obligatoria",
                "start": "06-11-2025 17:30",
                "end": "06-12-2025 23:59",
                "name": "Ejercicio Script Ubuntu (Tarea obligatoria)"
            },
            "36950": {
                "type": "Obligatoria",
                "start": "20-11-2025 17:20",
                "end": "14-01-2026 23:59",
                "name": "(RA3)Script con Windows (Configurar un script en Windows que contenga al menos 25 tarea obligatoria)"
            },
            "39151": {
                "type": "Obligatoria",
                "start": "18-12-2025 17:30",
                "end": "24-01-2026 23:59",
                "name": "(RA7) Tarea PowerShell_1 (primeros pasos - tarea obligatoria)"
            },
            "39152": {
                "type": "Obligatoria",
                "start": "18-12-2025 17:30",
                "end": "30-01-2026 23:59",
                "name": "(RA7) Ejercicio_1 PowerShell (Reto tarea obligatoria)"
            },
            "40906": {
                "type": "Obligatoria",
                "start": "22-01-2026 00:00",
                "end": "28-02-2026 23:00",
                "name": "RA4 - RELACION DE CONFIANZA ENTRE DOMINIOS"
            },
            "44956": {
                "type": "Obligatoria",
                "start": "11-02-2026 00:00",
                "end": "17-03-2026 23:59",
                "name": "RA2 tarea documentar Red entre Windows y Ubuntu"
            }
            
        },
        "tests": {
            "ASO-DICIEMBRE-REPASO-01": {
                "type": "Cuestionario",
                "start": "",
                "end": "",
                "name": "Repaso previo 1ª autoevaluación 1"
            },
            "ASO-DICIEMBRE-REPASO-02": {
                "type": "Cuestionario",
                "start": "",
                "end": "",
                "name": "Repaso previo 1ª autoevaluación 2"
            },
            "ASO-DICIEMBRE": {
                "type": "Cuestionario",
                "start": "",
                "end": "",
                "name": "AUTOEVALUACIÓN DICIEMBRE"
            },
            "ASO-ENERO-REPASO": {
                "type": "Cuestionario",
                "start": "",
                "end": "",
                "name": "Repaso previo examen Enero"
            },
            "ASO-ENERO": {
                "type": "Cuestionario",
                "start": "",
                "end": "",
                "name": "EXAMEN ENERO"
            },
            "ASO-FEBRERO-REPASO": {
                "type": "Cuestionario",
                "start": "",
                "end": "",
                "name": "Repaso previo 2ª autoevaluación"
            }
        },
        "notes": {
            "ASO-doc": {
                "name": "Apuntes ASO (doc)",
                "link": "https://docs.google.com/document/d/16WYQLS3ME0tRhn0M9ATMOQkpus3YQHmJxIZJ2hm-zno/edit?usp=sharing"
            },
            "ASO-LINUX-doc": {
                "name": "Apuntes ASO LINUX (doc)",
                "link": "https://docs.google.com/document/d/1QEuIaHtStbBaOU-TVhq_NBCaHvSyhKHUkDXKH8Lggg0/edit?usp=sharing"
            },
            "ISO-doc": {
                "name": "Apuntes ISO 1º (doc)",
                "link": "https://docs.google.com/document/d/17OCPjTD8RrtwGjszGxQEVBBY1L8voe5nbZnxG1R0tKA/edit?usp=sharing"
            }
        }
    },
    "CB": {
        "id": 593,
        "name": "Ciberseguridad",
        "teacher": "Carlos Quintana",
        "teacher_mail": "cquintana@digitechfp.com",
        "units": {
            "CB-1": {
                "folder": 37772,
                "folder_number": 1,
                "name": "Unidad 1. Introducción a la ciberseguridad",
                "link": "https://drive.google.com/file/d/1XS7cuMgCVG3aYCD-GHPfR4UTGfLd8-nL/view?usp=sharing"
            }
        },
        "resources": {
            "33031": {
                "name": "APUNTES CORTAFUEGOS FÍSICOS",
                "file": "ASA5505.docx",
                "link": "https://docs.google.com/document/d/1GyDs1CU9D0Hfa-wUqGfg2i6ZUQQ5NAks/edit?usp=sharing&ouid=117153571465087663660&rtpof=true&sd=true"
            },
            "34392": {
                "name": "Apuntes VPN",
                "file": "VPN.pdf",
                "link": "https://docs.google.com/document/d/15k8adQwJYA9HsRlFCNBl7ePvUb6LEc8s0x5N214mkiU/edit?usp=sharing"
            },
            "36099": {
                "name": "Apuntes seguridad por MAC",
                "file": "SEGURIDAD MAC.pdf",
                "link": "https://docs.google.com/document/d/1jz7E9k-zeVSnN-LCnHfeUKzC-6tGfBQpuExXSne_UYQ/edit?usp=sharing"
            },
            "33049": {
                "name": "Ejemplito de Cortafuegos Físicos",
                "file": "CORTAFUEGOS.pkt",
                "link": "https://drive.google.com/file/d/1YdqrdyYI9Yk6NyIGAvTTnOl66biFIv6c/view?usp=sharing"
            },
            "34396": {
                "name": "TOPOLOGÍA CORTAFUEGOS FISICOS (EJEMPLO DE CLASE)",
                "file": "CORTAFUEGOS-2.pkt",
                "link": "https://drive.google.com/file/d/1_P5vv6nYMfp_XLn1cB_oH867BbAfdjwu/view?usp=sharing"
            }
        },
        "tasks": {
            "36100": {
                "type": "Obligatoria",
                "start": "07-11-2025 20:30",
                "end": "16-12-2025 23:59",
                "name": "Ejercicio Cortafuegos, inalámbricas seguras y VPN (Tarea obligatoria)"
            },
            "36738": {
                "type": "Obligatoria",
                "start": "17-11-2025 20:25",
                "end": "22-12-2025 23:59",
                "name": "Vencimiento de (RA6 Y RA7) VPN_2 Y CORTAFUEGOS LÓGICOS (Tarea obligatoria)"
            }
        },
        "tests": {
            "CB-DICIEMBRE-REPASO": {
                "type": "Cuestionario",
                "start": "",
                "end": "",
                "name": "Repaso previo 1ª autoevaluación"
            },
            "CB-DICIEMBRE": {
                "type": "Cuestionario",
                "start": "",
                "end": "",
                "name": "AUTOEVALUACIÓN DICIEMBRE"
            },
            "CB-ENERO-REPASO": {
                "type": "Cuestionario",
                "start": "",
                "end": "",
                "name": "Repaso previo examen Enero"
            },
            "CB-ENERO": {
                "type": "Cuestionario",
                "start": "",
                "end": "",
                "name": "EXAMEN ENERO"
            },
            "CB-FEBRERO-REPASO": {
                "type": "Cuestionario",
                "start": "",
                "end": "",
                "name": "Repaso previo 2ª autoevaluación"
            }
        },
        "notes": {
            "CB-doc": {
                "name": "Apuntes CB (doc)",
                "link": "https://docs.google.com/document/d/1QrXXcxet-LuwRDo9N-zgI0zli8hcgBNlDZwnR3fPaa4/edit?usp=sharing"
            },
            "CB-01-doc": {
                "name": "Apuntes cortafuegos físicos (doc)",
                "file": "ASA5505.docx",
                "link": "https://docs.google.com/document/d/12HVSx2Fz_Lva6DjXolEG1t9KGy5nh_6gu1_wMHP9dQQ/edit?usp=sharing"
            },
            "CB-02-doc": {
                "name": "Apuntes VPN (doc)",
                "file": "VPN.pdf",
                "link": "https://docs.google.com/document/d/15k8adQwJYA9HsRlFCNBl7ePvUb6LEc8s0x5N214mkiU/edit?usp=sharing"
            },
            "CB-03-doc": {
                "name": "Apuntes seguridad por MAC (doc)",
                "file": "SEGURIDAD MAC.pdf",
                "link": "https://docs.google.com/document/d/1jz7E9k-zeVSnN-LCnHfeUKzC-6tGfBQpuExXSne_UYQ/edit?usp=sharing"
            },
            "CB-04-doc": {
                "name": "Apuntes Denegar Tráfico (PROXY) (doc)",
                "file": "APUNTESDENEGARTRAFICO.pdf",
                "link": "https://docs.google.com/document/d/1533EkY-9jJqa0ouYiT4TCwtVNj5-5TpBPmL6AA69Cuo/edit?usp=sharing"
            },
            "CB-05-doc": {
                "name": "Apuntes Netflow, Syslog, Sniffer (doc)",
                "file": "",
                "link": "https://docs.google.com/document/d/1_4izvTnz9wERLE305jD3IzEMdcYi_clA2c_b6jJphy8/edit?usp=sharing"
            }
        }
    },
    "DAPS": {
        "id": 583,
        "name": "Digitalización Aplicada al Sistema Productivo",
        "teacher": "Victor Manuel Aparicio",
        "teacher_mail": "victor.aparicio@digitechfp.com",
        "units": {
            "DAPS-1": {
                "folder": 36765,
                "folder_number": 2,
                "name": "Unidad 1. Creación de entornos IT OT",
                "link": "https://drive.google.com/file/d/1Gn_oxtDEqFh7Y5oaPfNR6Plkt7x6wUtu/view?usp=sharing"
            },
            "DAPS-2": {
                "folder": 36779,
                "folder_number": 3,
                "name": "Unidad 2. Tecnologías Habilitadoras Digitales",
                "link": "https://drive.google.com/file/d/1KDEAF52102AdPxzN1TaUR_EzPIhSH_Ou/view?usp=sharing"
            },
            "DAPS-3": {
                "folder": 36787,
                "folder_number": 4,
                "name": "Unidad 3. La nube",
                "link": "https://drive.google.com/file/d/1XTdmS5YHIz-tS2KoiLYaoQ48tPWNVwKg/view?usp=sharing"
            },
            "DAPS-4": {
                "folder": 36797,
                "folder_number": 5,
                "name": "Unidad 4. Herramientas Digitales",
                "link": "https://drive.google.com/file/d/1nV5h67qg4gS2f8TvGnYipP42MlHGZ11s/view?usp=sharing"
            }
        },
        "resources": {},
        "tasks": {
            "32811": {
                "type": "Obligatoria",
                "start": "09-10-2025 09:30",
                "end": "23-10-2025 11:30",
                "name": "ACTIVIDAD TEMA 1. OBLIGATORIA. DIGITALIZACIÓN. ENTORNOS IT Y OT"
            },
            "32831": {
                "type": "Complementaria",
                "start": "03-10-2025 09:30",
                "end": "17-10-2025 11:30",
                "name": "ACTIVIDAD COMPLEMENTARIA. TEMA 1 DIGITALIZACIÓN. LA DIGITALIZACIÓN. ENTORNOS IT Y OT"
            },
            "36111": {
                "type": "Obligatoria",
                "start": "08-11-2025 10:30",
                "end": "22-11-2025 10:30",
                "name": "ACTIVIDAD OBLIGATORIA TEMA 2. THD"
            },
            "36112": {
                "type": "Complementaria",
                "start": "08-11-2025 10:35",
                "end": "22-11-2025 10:35",
                "name": "ACTIVIDAD COMPLEMENTARIA TEMA 2. THD"
            },
            "38308": {
                "type": "Obligatoria",
                "start": "07-12-2025 19:00",
                "end": "29-12-2025 23:59",
                "name": "ACTIVIDAD OBLIGATORIA TEMA 3. LA NUBE DE GOOGLE"
            },
            "38307": {
                "type": "Complementaria",
                "start": "07-12-2025 19:00",
                "end": "29-12-2025 23:59",
                "name": "ACTIVIDAD COMPLEMENTARIA TEMA 3. LA NUBE DE GOOGLE"
            }
        },
        "tests": {
            "34104": {
                "type": "Cuestionario",
                "start": "",
                "end": "",
                "name": "CUESTIONARIO TEMA 1. DIGITALIZACIÓN. ENTORNOS IT Y OT"
            },
            "DAPS-DICIEMBRE": {
                "type": "Cuestionario",
                "start": "",
                "end": "",
                "name": "AUTOEVALUACIÓN DICIEMBRE"
            },
            "DAPS-ENERO": {
                "type": "Cuestionario",
                "start": "",
                "end": "",
                "name": "EXAMEN ENERO"
            }
        },
        "notes": {
            "DAPS-doc": {
                "name": "Apuntes DAPS (doc)",
                "link": "https://docs.google.com/document/d/1GYoO-eOPzh76NVoZX6WaHOH8gLfxFfNvw-_feuPXXck/edit?usp=sharing"
            }
        }
    },
    "IAW": {
        "id": 25,
        "name": "Implantación de aplicaciones web",
        "teacher": "Sara Gonzalo Rojo",
        "teacher_mail": "sgonzalo@digitechfp.com",
        "units": {
            "IAW-0": {
                "folder": 15474,
                "folder_number": 5,
                "name": "Conceptos generales de la arquitectura aplicaciones web",
                "link": "https://drive.google.com/file/d/1XTYFuBLCKcNKhglez_AXVgG1eSPP0jKY/view?usp=sharing"
            },
            "IAW-1": {
                "folder": 0,
                "folder_number": 0,
                "name": "Unidad 1.1. JavaScript Introducción",
                "link": "https://drive.google.com/file/d/1hHAxGlogU28-5afr-PcmMf09YHxlrMe0/view?usp=sharing"
            },
            "IAW-2": {
                "folder": 0,
                "folder_number": 0,
                "name": "Unidad 1.2. JavaScript. Operadores",
                "link": "https://drive.google.com/file/d/17uNbPBzFHgI3dhtUd0Q1_usLt6V_IdMo/view?usp=sharing"
            },
            "IAW-3": {
                "folder": 0,
                "folder_number": 0,
                "name": "Unidad 1.3. JavaScript. Bucles y estructuras de control",
                "link": "https://drive.google.com/file/d/1Kg4ZDEUZYoe03y9iQQWlCf7wjOn7Rqy2/view?usp=sharing"
            },
            "IAW-4": {
                "folder": 0,
                "folder_number": 0,
                "name": "Unidad 1.4. JavaScript. Arrays",
                "link": "https://drive.google.com/file/d/1OSi8Nt8ayARkLAKg9K9sBPcEKcNJtofd/view?usp=sharing"
            },
            "IAW-5": {
                "folder": 0,
                "folder_number": 0,
                "name": "Unidad 1.5. JavaScript. Funciones",
                "link": "https://drive.google.com/file/d/1sulIMesDFrZQXBrrdxcgtLrAvgupJH6s/view?usp=sharing"
            },
            "IAW-6": {
                "folder": 0,
                "folder_number": 0,
                "name": "Unidad 2. JavaScript. Gestión de eventos",
                "link": "https://drive.google.com/file/d/1XmqDrsyamIjMYD1IDxrVtLOuon4NPtCr/view?usp=sharing"
            },
            "IAW-7": {
                "folder": 0,
                "folder_number": 0,
                "name": "Unidad 2. JavaScript. Listado de eventos",
                "link": "https://drive.google.com/file/d/1x9HQLaC_-mV37VLYcb07ksYi8fZDxATi/view?usp=sharing"
            },
            "IAW-8": {
                "folder": 0,
                "folder_number": 0,
                "name": "Unidad 3. JavaScript. Gestión de nodos",
                "link": "https://drive.google.com/file/d/1Mscu6-oHnArFOl1kKI809yh2DXoc0mnf/view?usp=sharing"
            },
            "IAW-9": {
                "folder": 0,
                "folder_number": 0,
                "name": "Unidad 4. JavaScript. Objetos",
                "link": "https://drive.google.com/file/d/1W8HpZPeDPg9_VzKJJJhOaTu4VrTreFFi/view?usp=sharing"
            },
            "IAW-10": {
                "folder": 0,
                "folder_number": 0,
                "name": "Unidad 5. JavaScript. Clases",
                "link": "https://drive.google.com/file/d/15UNB0Xf_9iKrmtqd-5i3anE92jkFnXWS/view?usp=sharing"
            },
            "IAW-11": {
                "folder": 0,
                "folder_number": 0,
                "name": "Unidad 6.1 JavaScript. Array de objetos",
                "link": "https://drive.google.com/file/d/1AJfA3CdXjFbEqBtQ2g8CeyDyYyIjG164/view?usp=sharing"
            },
            "IAW-12": {
                "folder": 0,
                "folder_number": 0,
                "name": "Unidad 6.2 JavaScript. Json",
                "link": "https://drive.google.com/file/d/1rOKoyKLA86bqb69TtTfrgkeD4mNi1Jne/view?usp=sharing"
            }
        },
        "resources": {
            "32881": {
                "name": "Manual complementario HTML,CSS y JS",
                "file": "El+gran+libro+de+HTML5+CSS3+y+Javascrip.pdf",
                "link": "https://drive.google.com/file/d/1OgYWYltlNN_w63TSMXwdczR-kjhilI0Y/view?usp=sharing"
            }
        },
        "tasks": {
            "34421": {
                "type": "Obligatoria",
                "start": "21-10-2025 00:00",
                "end": "04-11-2025 23:59",
                "name": "Tarea JavaScript.OBLIGATORIA"
            },
            "34424": {
                "type": "Obligatoria",
                "start": "21-10-2025 00:00",
                "end": "04-11-2025 23:59",
                "name": "Tarea JavaScript II.OBLIGATORIA"
            },
            "35011": {
                "type": "Obligatoria",
                "start": "27-10-2025 00:00",
                "end": "10-11-2025 23:59",
                "name": "Tarea estructuras de control. OBLIGATORIA"
            },
            "35009": {
                "type": "Obligatoria",
                "start": "27-10-2025 00:00",
                "end": "10-11-2025 23:59",
                "name": "Tarea Bucles y estructuras de control. OBLIGATORIA"
            },
            "35704": {
                "type": "Obligatoria",
                "start": "04-11-2025 09:00",
                "end": "20-11-2025 23:59",
                "name": "Tarea Arrays. OBLIGATORIA"
            },
            "37437": {
                "type": "Obligatoria",
                "start": "25-11-2025 09:00",
                "end": "10-12-2025 23:59",
                "name": "Tarea Eventos.OBLIGATORIA"
            },
            "37867": {
                "type": "Obligatoria",
                "start": "01-12-2025 09:00",
                "end": "20-12-2025 23:59",
                "name": "Tarea Eventos II. OBLIGATORIA"
            },
            "38409": {
                "type": "Obligatoria",
                "start": "09-12-2025 09:00",
                "end": "15-01-2026 23:59",
                "name": "Tarea Gestión de nodos I.OBLIGATORIA"
            },
            "38406": {
                "type": "Obligatoria",
                "start": "09-12-2025 09:00",
                "end": "20-01-2026 23:59",
                "name": "Tarea Gestión de nodos II.OBLIGATORIA"
            },
            "40091": {
                "type": "Obligatoria",
                "start": "19-01-2026 09:00",
                "end": "08-02-2026 23:59",
                "name": "RA1-RA2-RA3-RA4 Práctica Visor.OBLIGATORIA"
            },
            "41343": {
                "type": "Obligatoria",
                "start": "27-01-2026 09:00",
                "end": "18-02-2026 23:59",
                "name": "RA1-RA2-RA3-RA4 Práctica Visor II.OBLIGATORIA"
            },
            "41712": {
                "type": "Obligatoria",
                "start": "02-02-2026 09:00",
                "end": "22-02-2026 23:59",
                "name": "RA1-RA2-RA3-RA4 Práctica Maquetación web con nodos.OBLIGATORIA"
            },
            "41785": {
                "type": "Obligatoria",
                "start": "06-02-2026 09:00",
                "end": "25-02-2026 23:59",
                "name": "RA1-RA2-RA3-RA4-RA5 Práctica nodos y objetos"
            },
            "44682": {
                "type": "Obligatoria",
                "start": "09-02-2026 14:03",
                "end": "17-03-2026 23:59",
                "name": "RA5 Práctica trabajo con clases"
            },
            "45339": {
                "type": "Obligatoria",
                "start": "16-02-2026 09:00",
                "end": "02-03-2026 23:59",
                "name": "RA5 Práctica trabajo con clases. II"
            }
        },
        "tests": {
            "IAW-DICIEMBRE": {
                "type": "Cuestionario",
                "start": "",
                "end": "",
                "name": "AUTOEVALUACIÓN DICIEMBRE"
            },
            "IAW-ENERO": {
                "type": "Cuestionario",
                "start": "",
                "end": "",
                "name": "EXAMEN ENERO"
            }
        },
        "notes": {
            "IAW-doc": {
                "name": "Apuntes IAW (doc)",
                "link": "https://docs.google.com/document/d/1VPF808Y5k3zBbg8tPUewvFMKnqC8loSodSYEZpCntdQ/edit?usp=sharing"
            }
        }
    },
    "IPE": {
        "id": 600,
        "name": "Itinerario Personal para la Empleabilidad II",
        "teacher": "Victor Manuel Aparicio",
        "teacher_mail": "victor.aparicio@digitechfp.com",
        "units": {
            "IPE-1": {
                "folder": 37597,
                "folder_number": 2,
                "name": "Unidad 1. La búsqueda de empleo",
                "link": "https://drive.google.com/file/d/1BnKQHOP0NWu86uF8hznbmKCq6FVArZaB/view?usp=sharing"
            },
            "IPE-2": {
                "folder": 37604,
                "folder_number": 2,
                "name": "Unidad 2. Estrategias para la mejora de la empleabilidad",
                "link": "https://drive.google.com/file/d/1suXahjLauUq-1QgAglhIEcCMLsbJ-kTG/view?usp=sharing"
            },
            "IPE-3": {
                "folder": 37610,
                "folder_number": 3,
                "name": "Unidad 3. El emprendedor y la idea emprendedora",
                "link": "https://drive.google.com/file/d/1jwlRDj8UY5ElgWEXAs9n2lQBS1-_Xr3T/view?usp=sharing"
            }
        },
        "resources": {},
        "tasks": {
            "36526": {
                "type": "Obligatoria",
                "start": "13-11-2025 20:30",
                "end": "27-11-2025 20:30",
                "name": "TAREA OBLIGATORIA TEMA 1. BÚSQUEDA ACTIVA DE EMPLEO"
            },
            "36527": {
                "type": "Complementaria",
                "start": "13-11-2025 20:30",
                "end": "27-11-2025 20:30",
                "name": "ACTIVIDAD COMPLEMENTARIA TEMA 1. BÚSQUEDA ACTIVA DE EMPLEO"
            },
            "41767": {
                "type": "Obligatoria",
                "start": "02-02-2026 20:30",
                "end": "16-02-2026 23:59",
                "name": "ACTIVIDAD OBLIGATORIA TEMA 2. ESTRATEGIAS PARA LA MEJORA DE LA EMPLEABILIDAD"
            },
            "41768": {
                "type": "Complementaria",
                "start": "02-02-2026 20:30",
                "end": "16-02-2026 23:59",
                "name": "ACTIVIDAD COMPLEMENTARIA TEMA 2. ESTRATEGIAS PARA LA MEJORA DE LA EMPLEABILIDAD"
            }
        },
        "tests": {
            "36484": {
                "type": "Cuestionario",
                "start": "",
                "end": "",
                "name": "CUESTIONARIO 1. BÚSQUEDA ACTIVA DE EMPLEO"
            },
            "IPE-DICIEMBRE": {
                "type": "Cuestionario",
                "start": "",
                "end": "",
                "name": "AUTOEVALUACIÓN DICIEMBRE"
            },
            "IPE-ENERO": {
                "type": "Cuestionario",
                "start": "",
                "end": "",
                "name": "EXAMEN ENERO"
            }
        },
        "notes": {
            "IPE-doc": {
                "name": "Apuntes IPE (doc)",
                "link": "https://docs.google.com/document/d/1hV-HHRQfjabXeDla6K1usL2Rt5uitLUXn2s1JI72Xz8/edit?usp=sharing"
            }
        }
    },
    "SAD": {
        "id": 21,
        "name": "Seguridad y alta disponibilidad",
        "teacher": "Rafael Chacón",
        "teacher_mail": "rafa.chacon.almeda@digitechfp.com",
        "units": {
            "SAD-1": {
                "folder": 18346,
                "folder_number": 1,
                "name": "Unidad 1.1 Adopción de pautas de seguridad informática",
                "link": "https://drive.google.com/file/d/1HxYrjmYHbgmPD2vYBmBAQp1TdtKwgc2K/view?usp=sharing"
            },
            "SAD-2": {
                "folder": 18347,
                "folder_number": 2,
                "name": "Unidad 1.2 Elementos vulnerables de los sistemas informáticos",
                "link": "https://drive.google.com/file/d/12U8rTkEIM2qW8dY4HckwgvkBcHyhKsJ1/view?usp=sharing"
            },
            "SAD-3": {
                "folder": 18348,
                "folder_number": 3,
                "name": "Unidad 1.3 Tipos de seguridad informática",
                "link": "https://drive.google.com/file/d/1Sjk_22qgCAYCS4ECaA_gxM1Krnuc_-xq/view?usp=sharing"
            },
            "SAD-4": {
                "folder": 0,
                "folder_number": 4,
                "name": "Unidad 2.1 Implantación de mecanismos de seguridad activa",
                "link": "https://drive.google.com/file/d/1aAfFLBHn6JBo1gmFY_1f7LVyx-unXwEH/view?usp=sharing"
            },
            "SAD-5": {
                "folder": 0,
                "folder_number": 4,
                "name": "Unidad 2.2 Control de accesos lógicos",
                "link": "https://drive.google.com/file/d/1nJOZbATpEVURQMQ-nraDNm_snxhDOpX3/view?usp=sharing"
            },
            "SAD-6": {
                "folder": 0,
                "folder_number": 4,
                "name": "Unidad 2.3 Ataques informáticos y contramedidas",
                "link": "https://drive.google.com/file/d/1EhmECfiXPKR7fkeLAzaE1NYX3BP1eOm6/view?usp=sharing"
            },
            "SAD-7": {
                "folder": 0,
                "folder_number": 4,
                "name": "Unidad 2.4 Introducción a la auditoría de seguridad informática",
                "link": "https://drive.google.com/file/d/1dqru7JgWj3UUN25Ckl7nnqwLbztJIQrP/view?usp=sharing"
            },
            "SAD-8": {
                "folder": 0,
                "folder_number": 4,
                "name": "Unidad 2.5 Herramientas de auditoría informática",
                "link": "https://drive.google.com/file/d/1Xa1mBq9U3ksBklXvWdVbhqHw0Etqh9Gt/view?usp=sharing"
            },
            "SAD-9": {
                "folder": 0,
                "folder_number": 4,
                "name": "Unidad 2.6 Wireshark",
                "link": "https://drive.google.com/file/d/1nhGKVYTBDtHdUXjT8ujNaZA_1Am7kgC_/view?usp=sharing"
            },
            "SAD-10": {
                "folder": 0,
                "folder_number": 4,
                "name": "Unidad 2.7 Sistema de cifrado",
                "link": "https://drive.google.com/file/d/1MwlwtAL5-sLEBMvA4089ZPLUi4lZ4so3/view?usp=sharing"
            }
        },
        "units-alt": {
            "SAD-UD1": {
                "name": "Unidad 1. Introducción a la seguridad informática"
            },
            "SAD-UD2": {
                "name": "Unidad 2. Implantación de mecanismos de seguridad activa"
            },
            "SAD-UD3": {
                "name": "Unidad 3. Implantación de seguridad perimetral"
            },
            "SAD-UD4": {
                "name": "Unidad 4. Instalación y configuración de cortafuegos"
            },
            "SAD-UD5": {
                "name": "Unidad 5. instalación y configuración de servidores proxy"
            },
            "SAD-UD6": {
                "name": "Unidad 6. Implantación de técnicas de acceso remoto. VPNs (Virtual Private Network)"
            },
            "SAD-UD7": {
                "name": "Unidad 7. Implantación  de soluciones de alta disponibilidad"
            }
        },
        "resources": {},
        "tasks": {
            "2406": {
                "type": "Obligatoria",
                "start": "30-09-2025 23:59",
                "end": "22-10-2025 23:59",
                "name": "Vencimiento de Tarea 1 - Adopción de pautas de seguridad informática OBLIGATORIA"
            },
            "4485": {
                "type": "Obligatoria",
                "start": "23-10-2025 00:00",
                "end": "23-11-2025 23:59",
                "name": "Tarea 2 - Implantando medidas de seguridad - OBLIGATORIA"
            },
            "2884": {
                "type": "Obligatoria",
                "start": "17-12-2025 21:00",
                "end": "25-01-2026 23:59",
                "name": "Tarea 3 - Comenzamos a escanear con nmap (RA3) - OBLIGATORIA"
            },
            "2885": {
                "type": "Complementaria",
                "start": "17-12-2025 21:00",
                "end": "25-01-2026 23:59",
                "name": "Actividad 02_01 Prácticas avanzadas con nmap"
            },
            "4486": {
                "type": "Complementaria",
                "start": "21-02-2026 21:00",
                "end": "15-03-2026 23:59",
                "name": "Tarea 4 - IDS e IPS (RA5) - OBLIGATORIA"
            }
        },
        "tests": {
            "17233": {
                "type": "Cuestionario",
                "start": "",
                "end": "",
                "name": "Cuestionario - Introducción"
            },
            "SAD-DICIEMBRE": {
                "type": "Cuestionario",
                "start": "",
                "end": "",
                "name": "AUTOEVALUACIÓN DICIEMBRE"
            },
            "SAD-ENERO": {
                "type": "Cuestionario",
                "start": "",
                "end": "",
                "name": "EXAMEN ENERO"
            },
            "17235": {
                "type": "Cuestionario",
                "start": "",
                "end": "",
                "name": "Seguridad activa y acceso remoto"
            }
        },
        "notes": {
            "SAD-doc": {
                "name": "Apuntes SAD (gdoc)",
                "link": "https://docs.google.com/document/d/1bhVHYp2RQ0okuV_tHYmvvs3-eaP-jO_myU3DXYBxcRQ/edit?usp=sharing"
            },
            "SAD-RES-doc": {
                "name": "Resumen SAD (gdoc)",
                "link": "https://docs.google.com/document/d/1PT2J9N3FOELOWx9u8_kFxxYi7yCqX3vhkK-MQH2yvcM/edit?usp=sharing"
            }
        }
    },
    "SAPS": {
        "id": 584,
        "name": "Sostenibilidad Aplicada al Sistema Productivo",
        "teacher": "Victor Manuel Aparicio",
        "teacher_mail": "victor.aparicio@digitechfp.com",
        "units": {
            "SAPS-1": {
                "folder": 36764,
                "folder_number": 2,
                "name": "Unidad 1. La economía lineal y circular",
                "link": "https://drive.google.com/file/d/1WU3E30CvCJEHwCtD3lr34pwd-HCILtqn/view?usp=sharing"
            },
            "SAPS-2": {
                "folder": 36781,
                "folder_number": 3,
                "name": "Unidad 2. Contribución de las empresas al desarrollo sostenible",
                "link": "https://drive.google.com/file/d/15fGcet9l8XgdYlll3IxL4H9ABGXxr0vX/view?usp=sharing"
            },
            "SAPS-3": {
                "folder": 36791,
                "folder_number": 5,
                "name": "Unidad 3. Retos ambientales y sociales",
                "link": "https://drive.google.com/file/d/1ukJPHQsjQrLS_EaoN6hPr0yTOmDGLgZ2/view?usp=sharing"
            }
        },
        "resources": {},
        "tasks": {
            "37323": {
                "type": "Obligatoria",
                "start": "23-11-2025 13:00",
                "end": "07-12-2025 13:00",
                "name": "ACTIVIDAD OBLIGATORIA TEMA 1. LA ECONOMÍA LINEAL Y CIRCULAR"
            },
            "37324": {
                "type": "Complementaria",
                "start": "23-11-2025 13:00",
                "end": "07-12-2025 13:00",
                "name": "ACTIVIDAD COMPLEMENTARIA TEMA 1. LA ECONOMÍA LINEAL Y CIRCULAR"
            },
            "41476": {
                "type": "Obligatoria",
                "start": "28-01-2026 15:00",
                "end": "10-02-2026 23:59",
                "name": " ACTIVIDAD OBLIGATORIA TEMA 2. CONTRIBUCIÓN DE LAS EMPRESAS CON EL DESARROLLO SOSTENIBLE"
            },
            "41478": {
                "type": "Complementaria",
                "start": "28-01-2026 15:00",
                "end": "10-02-2026 23:59",
                "name": "ACTIVIDAD COMPLEMENTARIA TEMA 2. CONTRIBUCIÓN DE LAS EMPRESAS CON EL DESARROLLO SOSTENIBLE"
            }
        },
        "tests": {
            "37408": {
                "type": "Cuestionario",
                "start": "",
                "end": "",
                "name": "CUESTIONARIO TEMA 1. LA ECONOMÍA LINEAL Y CIRCULAR"
            },
            "SAPS-DICIEMBRE": {
                "type": "Cuestionario",
                "start": "",
                "end": "",
                "name": "AUTOEVALUACIÓN DICIEMBRE"
            },
            "SAPS-ENERO": {
                "type": "Cuestionario",
                "start": "",
                "end": "",
                "name": "EXAMEN ENERO"
            }
        },
        "notes": {
            "SAPS-doc": {
                "name": "Apuntes SAPS (doc)",
                "link": "https://docs.google.com/document/d/1GPSXc1NUYc8ctq-ZHu6X3iXYIRUS2DuuwMpwGoO0l90/edit?usp=sharing"
            }
        }
    },
    "SRI": {
        "id": 22,
        "name": "Servicios de red e Internet",
        "teacher": "Carlos Quintana",
        "teacher_mail": "cquintana@digitechfp.com",
        "units": {
            "SRI-0": {
                "folder": 16977,
                "folder_number": 2,
                "name": "Instalación y administración de servicios de nombres de dominio (Cisco)",
                "link": "https://drive.google.com/file/d/1tTXj5GSPJeBj5G0jhM3efP597wxXZSOx/view?usp=sharing"
            }
        },
        "tasks": {
            "33394": {
                "type": "Obligatoria",
                "start": "09-10-2025 09:30",
                "end": "27-10-2025 23:59",
                "name": "Ejercicio IPV4-IPV6con teléfonos y tunnel. OBLIGATORIA"
            },
            "36816": {
                "type": "Obligatoria",
                "start": "17-11-2025 23:59",
                "end": "14-01-2026 23:59",
                "name": "(RA1-RA2-RA3) CLOUD 10 ROUTER CON SERVIDORES Y DHCP-RELAY"
            },
            "39188": {
                "type": "Obligatoria",
                "start": "19-12-2025 19:00",
                "end": "30-01-2026 23:59",
                "name": "(RA1)Tarea Sumarizar en IPV4"
            },
            "39189": {
                "type": "Obligatoria",
                "start": "19-12-2025 19:00",
                "end": "30-01-2026 23:59",
                "name": "(RA1)Tarea Sumarizar en IPv6"
            }
        },
        "resources": {
            "1": {
                "name": "APUNTES 30%: APUNTESEIGRPIPV4 (3).docx",
                "file": "APUNTESEIGRPIPV4 (3).docx",
                "link": "https://docs.google.com/document/d/10wGhop4ua_pSN5TghszMkst_VgzJoE1C/edit?usp=sharing&ouid=117153571465087663660&rtpof=true&sd=true"
            },
            "2": {
                "name": "APUNTES 30%: ApuntesSSH.docx",
                "file": "ApuntesSSH.docx",
                "link": "https://docs.google.com/document/d/11LGyxzhRfrWN5XUuqXvvzIEpz25xyE78/edit?usp=sharing&ouid=117153571465087663660&rtpof=true&sd=true"
            },
            "3": {
                "name": "APUNTES 30%: APUNTES DHCP-RELAY.docx",
                "file": "APUNTES DHCP-RELAY.docx",
                "link": "https://docs.google.com/document/d/11YFxZxZoME-AJ9ylDq5VVl8icuaRbKXY/edit?usp=sharing&ouid=117153571465087663660&rtpof=true&sd=true"
            },
            "4": {
                "name": "APUNTES 30%: APUNTESNETFLOW.docx",
                "file": "APUNTESNETFLOW.docx",
                "link": "https://docs.google.com/document/d/12r2KfCupvfhXFnY9aFOwB0U1lE7W4mQA/edit?usp=sharing&ouid=117153571465087663660&rtpof=true&sd=true"
            },
            "5": {
                "name": "APUNTES 30%: TFTP.docx",
                "file": "TFTP.docx",
                "link": "https://docs.google.com/document/d/13c1GB0_3w1n3I3jg3Sd2sW9SEbYrJx4J/edit?usp=sharing&ouid=117153571465087663660&rtpof=true&sd=true"
            },
            "6": {
                "name": "APUNTES 30%: ASA5505 CON FORMATO.docx",
                "file": "ASA5505 CON FORMATO.docx",
                "link": "https://docs.google.com/document/d/13ezAwm6ixdEiywUMnE3_nBC5VOqt2XkX/edit?usp=sharing&ouid=117153571465087663660&rtpof=true&sd=true"
            },
            "7": {
                "name": "APUNTES 30%: APUNTESDENEGARTRAFICOIPV6.docx",
                "file": "APUNTESDENEGARTRAFICOIPV6.docx",
                "link": "https://docs.google.com/document/d/16G3YUQwghY0GK2RB1hlt7c0TfCpNFEGQ/edit?usp=sharing&ouid=117153571465087663660&rtpof=true&sd=true"
            },
            "8": {
                "name": "APUNTES 30%: AAATacacsLoginyEnable.docx",
                "file": "AAATacacsLoginyEnable.docx",
                "link": "https://drive.google.com/file/d/16KGXxz7cc5yz6yl4TsmQnLq6GgFuXIoP/view?usp=sharing"
            },
            "9": {
                "name": "APUNTES 30%: ASA5505.docx",
                "file": "ASA5505.docx",
                "link": "https://docs.google.com/document/d/1Bk74vEXmqA412-eNmlwqbOpLN99puS5k/edit?usp=sharing&ouid=117153571465087663660&rtpof=true&sd=true"
            },
            "10": {
                "name": "APUNTES 30%: telnet.docx",
                "file": "telnet.docx",
                "link": "https://drive.google.com/file/d/1Cu_fwbVZb6FGZ0hsc-Y5vjU89clUHQ0e/view?usp=sharing"
            },
            "11": {
                "name": "APUNTES 30%: APUNTESEIGRPIPV4.docx",
                "file": "APUNTESEIGRPIPV4.docx",
                "link": "https://docs.google.com/document/d/1D-mOnD7tNoPhMWLDKrxEiIyk8r9z3aWU/edit?usp=sharing&ouid=117153571465087663660&rtpof=true&sd=true"
            },
            "12": {
                "name": "APUNTES 30%: VPN.pdf",
                "file": "VPN.pdf",
                "link": "https://docs.google.com/document/d/1FtaxuljPyPguU5qGag8nwYpGwqf_XTPy/edit?usp=sharing&ouid=117153571465087663660&rtpof=true&sd=true"
            },
            "13": {
                "name": "APUNTES 30%: APUNTES NETFLOW_ACTUALIZADO.docx",
                "file": "APUNTES NETFLOW_ACTUALIZADO.docx",
                "link": "https://docs.google.com/document/d/1Ilw1CZWYT83t-IVaP-Dukawwk2VG8EpG/edit?usp=sharing&ouid=117153571465087663660&rtpof=true&sd=true"
            },
            "14": {
                "name": "APUNTES 30%: SWTICH3CAPAS.docx",
                "file": "SWTICH3CAPAS.docx",
                "link": "https://docs.google.com/document/d/1MUOgjO5S2Y7qg55D51wC8nW97z4TnhP-/edit?usp=sharing&ouid=117153571465087663660&rtpof=true&sd=true"
            },
            "15": {
                "name": "APUNTES 30%: APUNTESDENEGARTRAFICO.pdf",
                "file": "APUNTESDENEGARTRAFICO.pdf",
                "link": "https://docs.google.com/document/d/1O1eZjvjVFA0GOFy8QqRJTFtRWpm84bpG/edit?usp=sharing&ouid=117153571465087663660&rtpof=true&sd=true"
            },
            "17": {
                "name": "APUNTES 30%: SEGURIDADMAC_con formato.docx",
                "file": "SEGURIDADMAC_con formato.docx",
                "link": "https://docs.google.com/document/d/1UxZmLeinphsyQZhtNQhwCliwYz93TwZ6/edit?usp=sharing&ouid=117153571465087663660&rtpof=true&sd=true"
            },
            "18": {
                "name": "APUNTES 30%: ASA5505_SINFORMATO.docx",
                "file": "ASA5505_SINFORMATO.docx",
                "link": "https://drive.google.com/file/d/1W9jIsPyRkQoMQNCL2hF1PcchunVZnLWv/view?usp=sharing"
            },
            "19": {
                "name": "APUNTES 30%: ~$UNTES TUNNEL IPV6 E IPV4.docx",
                "file": "~$UNTES TUNNEL IPV6 E IPV4.docx",
                "link": "https://docs.google.com/document/d/1ZWz_l3deCvWsWuJBNGA7yOjXIEEbqprC/edit?usp=sharing&ouid=117153571465087663660&rtpof=true&sd=true"
            },
            "25": {
                "name": "APUNTES 30%: TUNNEL IPV6 E IPV4.docx",
                "file": "APUNTES TUNNEL IPV6 E IPV4.docx",
                "link": "https://docs.google.com/document/d/1lY7_oAWwLQcK9Bo7WYXrYtAIysvh7L-s/edit?usp=sharing&ouid=117153571465087663660&rtpof=true&sd=true"
            },
            "21": {
                "name": "APUNTES 30%: SYSLOG.docx",
                "file": "SYSLOG.docx",
                "link": "https://docs.google.com/document/d/1as_TkXcW91u5LIz1goVgmq-Y1cvnCS7z/edit?usp=sharing&ouid=117153571465087663660&rtpof=true&sd=true"
            },
            "22": {
                "name": "APUNTES 30%: NAT.docx",
                "file": "NAT.docx",
                "link": "https://docs.google.com/spreadsheets/d/1gfoxH6kJabP19i9MkuQE9jq0PWpcrfx1/edit?usp=sharing&ouid=117153571465087663660&rtpof=true&sd=true"
            },
            "23": {
                "name": "APUNTES 30%: VPN_FORMATO.docx",
                "file": "VPN_FORMATO.docx",
                "link": "https://drive.google.com/file/d/1gsm_Zm4RvJ48LG5jPHPRVBvr5dwCqwwN/view?usp=sharing"
            },
            "26": {
                "name": "APUNTES 30%: VPNASA5505.docx",
                "file": "VPNASA5505.docx",
                "link": "https://docs.google.com/document/d/1meFpEA6p6GJDD5HCJ33W-CtdF9TphRZ9/edit?usp=sharing&ouid=117153571465087663660&rtpof=true&sd=true"
            },
            "27": {
                "name": "APUNTES 30%: PLANTILLA CALCULAR SUBNETING_IPV6_SUMARIZAR.xlsx",
                "file": "PLANTILLA CALCULAR SUBNETING_IPV6_SUMARIZAR.xlsx",
                "link": "https://docs.google.com/document/d/1stKNDrRK9WmQkmwxM1C3oYyY7XPH1oS6/edit?usp=sharing&ouid=117153571465087663660&rtpof=true&sd=true"
            },
            "28": {
                "name": "APUNTES 30%: SEGURIDADMAC.pdf",
                "file": "SEGURIDADMAC.pdf",
                "link": "https://docs.google.com/document/d/1uI2-6XkFuvO44DKmgTqkMm19sOcUtqIn/edit?usp=sharing&ouid=117153571465087663660&rtpof=true&sd=true"
            },
            "29": {
                "name": "APUNTES 30%: OSPF.pdf",
                "file": "OSPF.pdf",
                "link": "https://docs.google.com/document/d/1v0OUAmw3DNBN4j1eFxSvL5Nuzmx_lzTL/edit?usp=sharing&ouid=117153571465087663660&rtpof=true&sd=true"
            },
            "30": {
                "name": "APUNTES 30%: ssh_asa5505.docx",
                "file": "ssh_asa5505.docx",
                "link": "https://docs.google.com/document/d/1vzx150zqejmmdoZv81pOrq3iGfxYjpxj/edit?usp=sharing&ouid=117153571465087663660&rtpof=true&sd=true"
            },
            "31": {
                "name": "APUNTES 30%: APUNTESOSPFIPV4EIPV6.pdf",
                "file": "APUNTESOSPFIPV4EIPV6.pdf",
                "link": "https://drive.google.com/file/d/1wN7PzIPc2rw-CeAzsFAYzK7r3cde_gNH/view?usp=sharing"
            },
            "32": {
                "name": "APUNTES 30%: ApuntesSniffer.docx",
                "file": "ApuntesSniffer.docx",
                "link": "https://docs.google.com/document/d/1wcon_HkKXCe4mMzc5ebAXkYS93r31y64/edit?usp=sharing&ouid=117153571465087663660&rtpof=true&sd=true"
            },
            "33": {
                "name": "APUNTES 30%: ~$UNTES DHCP-RELAY.docx",
                "file": "~$UNTES DHCP-RELAY.docx",
                "link": "https://docs.google.com/document/d/1xAu_oN1DEqzbyKtITBNu5yci7hpK7wXU/edit?usp=sharing&ouid=117153571465087663660&rtpof=true&sd=true"
            }
        },
        "tests": {
            "SRI-DICIEMBRE-REPASO": {
                "type": "Cuestionario",
                "start": "",
                "end": "",
                "name": "Repaso previo 1ª autoevaluación"
            },
            "SRI-DICIEMBRE": {
                "type": "Cuestionario",
                "start": "",
                "end": "",
                "name": "AUTOEVALUACIÓN DICIEMBRE"
            },
            "SRI-ENERO-REPASO": {
                "type": "Cuestionario",
                "start": "",
                "end": "",
                "name": "Repaso previo examen Enero"
            },
            "SRI-ENERO": {
                "type": "Cuestionario",
                "start": "",
                "end": "",
                "name": "EXAMEN ENERO"
            },
            "SRI-FEBRERO-REPASO": {
                "type": "Cuestionario",
                "start": "",
                "end": "",
                "name": "Repaso previo 2ª autoevaluación"
            }
        },
        "notes": {
            "SRI-doc": {
                "name": "Apuntes SRI (doc)",
                "link": "https://docs.google.com/document/d/1fqztidnHYGfsdQ1egcmHmEac8NpaEWBg6u7OqC6pQcM/edit?usp=sharing"
            },
            "SRI-chuleta-doc": {
                "name": "CHULETA PAR 1º",
                "link": "https://docs.google.com/document/d/1Bj6twOCcQJBz4Mtu_XxZdif5tVIQvLpweXHg1gPn7uI/edit?usp=sharing"
            },
            "SRI-calculadora": {
                "name": "CALCULADORA BÄSICA",
                "link": "https://docs.google.com/spreadsheets/d/1LTd9LyWcneUbbZXBWeUk28-lf3tMkZb32BGJ_TAG6hg/edit?usp=sharing"
            },            
            "SRI-AP30-24-doc": {
                "name": "Tunnel IPv6 e IPv4 (doc)",
                "file": "APUNTESTUNNELIPV6EIPV4.docx",
                "link": "https://docs.google.com/document/d/1J6KSK4KQttlRTRwgp4wRvweKkSkQkmzifGU4Nze06pU/edit?usp=sharing"
            },
            "SRI-AP30-20-doc": {
                "name": "VLAN IPv6 (doc)",
                "file": "APUNTESVLANIPV6.pdf",
                "link": "https://docs.google.com/document/d/1c97uLVAfA7e7_dA6MJdYGn5Z5MVC9kA7jxB-h6r3wlw/edit?usp=sharing"
            },
            "SRI-AP30-16-doc": {
                "name": "VLAN IPv6 con telefonía (doc)",
                "file": "APUNTESVLANIPV4CONTELEFONIA.pdf",
                "link": "https://docs.google.com/document/d/17fMA46fJ8lTVFXLZOIyFU4ZvFWPQSpaBut-YW77gooM/edit?usp=sharing"
            },
            "SRI-IPv6_route_alias-doc": {
                "name": "Enrutamientos IPv6 por alias (doc)",
                "file": "APUNTES ENRUTAMIENTOS ALIAS IPV6.docx",
                "link": "https://docs.google.com/document/d/11BqdSnNxV36Veb5wwDbihH7ZWQt5zPJQnoSF9nK1sxY/edit?usp=sharing"
            },
            "SRI-OSPF-doc": {
                "name": "OSPF IPv4 - IPv6 (doc)",
                "file": "OSPF IPV4  IPV6.docx",
                "link": "https://docs.google.com/document/d/10LZFzOZQ91M2FpA0bqQ7-P0l7vtJHxcaj6oYC7i4XRM/edit?usp=sharing"
            }
        }
    },
    "TE": {
        "id": 23,
        "name": "Technical English",
        "teacher": "Raquel Ujaque",
        "teacher_mail": "rujaque@digitechfp.com",
        "units": {
            "TE-0": {
                "folder": 16446,
                "folder_number": 1,
                "name": "Unidad 0. Introduction",
                "link": "https://drive.google.com/file/d/1ZHb25qE9ci_3kqhzj3nfQCTQRLT5phQd/view?usp=sharing"
            },
            "TE-1": {
                "folder": 47829,
                "folder_number": 5,
                "name": "UNIT 1. Present Tenses",
                "link": "https://drive.google.com/file/d/1B-e3DWKMF3kRNK-vnzzYetpvO81xvBPn/view?usp=sharing"
            },
            "TE-2": {
                "folder": 47830,
                "folder_number": 6,
                "name": "UNIT 2. Past Tenses",
                "link": "https://drive.google.com/file/d/1sGsEEaXEStey93-LgXUOD63g3l4hoV4p/view?usp=sharing"
            },
            "TE-3": {
                "folder": 47831,
                "folder_number": 7,
                "name": "UNIT 3. Perfect Tenses",
                "link": "https://drive.google.com/file/d/110arYxEpyzyW5zniTSZvYK9uDPpByN5K/view?usp=sharing"
            },
            "TE-4": {
                "folder": 47832,
                "folder_number": 8,
                "name": "UNIT 4. Future Tenses",
                "link": "https://drive.google.com/file/d/1i2pP9T32vx5lTG2dd5YTFfECdhcHsZJK/view?usp=sharing"
            },
            "TE-5": {
                "folder": 47833,
                "folder_number": 8,
                "name": "UNIT 5. Modal Tenses",
                "link": "https://drive.google.com/file/d/1PywhMxiluR9lJ_IPoAYHuZsgkWL2Rjnl/view?usp=sharing"
            },
            "TE-6": {
                "folder": 47974,
                "folder_number": 11,
                "name": "UNIT 6. Conditional Tenses",
                "link": "https://drive.google.com/file/d/16COSI3nI-xK28gv_ysLTKdQCRJOkNZwI/view?usp=sharing"
            },
            "TE-7": {
                "folder": 47835,
                "folder_number": 11,
                "name": "UNIT 7. Passive Voice",
                "link": "https://drive.google.com/file/d/1g6sx8ywrLgMrwKSn__eJgdJ8To-Ih-xw/view?usp=sharing"
            } ,
            "TE-8": {
                "folder": 47836,
                "folder_number": 11,
                "name": "UNIT 8. Relative Clauses",
                "link": "https://drive.google.com/file/d/1lQH4sZKoRZsJGW7tKCRvA4hSRCxmnDwn/view?usp=sharing"
            } 
        },
        "resources": {
            "TE-1": {
                "status": "downloaded",
                "name": "Technical Vocabulary",
                "file": "Technical Vocabulary.pdf",
                "link": "https://drive.google.com/file/d/1xPmpN4DY26JrSxAPnnYukyfDAQpX6YZ8/view?usp=sharing"
            }
        },
        "tasks": {
            "14072": {
                "type": "Obligatoria",
                "start": "01-10-2025 00:00",
                "end": "21-10-2025 23:59",
                "name": "Introduction Task. MANDATORY"
            },
            "14075": {
                "type": "Obligatoria",
                "start": "21-10-2025 08:00",
                "end": "03-11-2025 23:59",
                "name": "UNIT 1. Task - MANDATORY"
            },
            "14080": {
                "type": "Obligatoria",
                "start": "29-10-2025 17:20",
                "end": "11-11-2025 23:59",
                "name": "UNIT 2. Task - MANDATORY"
            },
            "18254": {
                "type": "Obligatoria",
                "start": "12-11-2025 19:00",
                "end": "25-11-2025 23:59",
                "name": "UNIT 3. Task - compulsory"
            },
            "14090": {
                "type": "Obligatoria",
                "start": "26-11-2025 15:55",
                "end": "09-12-2025 23:59",
                "name": "UNIT 4. Task - compulsory"
            },
            "38570": {
                "type": "Obligatoria",
                "start": "10-12-2025 19:00",
                "end": "11-01-2026 23:59",
                "name": "LISTENING UNIT 4 - COMPULSORY"
            },
            "14094": {
                "type": "Obligatoria",
                "start": "13-01-2026 17:00",
                "end": "27-01-2026 23:59",
                "name": "UNIT 5. Task - compulsory RA1,2,4"
            },
            "14099": {
                "type": "Obligatoria",
                "start": "28-01-2026 11:55",
                "end": "10-02-2026 23:59",
                "name": "UNIT 6. Task - compulsory RA1,2,3,4"
            },
            "14103": {
                "type": "Obligatoria",
                "start": "03-02-2026 07:55",
                "end": "22-02-2026 23:59",
                "name": "UNIT 7. Task - compulsory RA1,3"
            },
            "14108": {
                "type": "Obligatoria",
                "start": "18-02-2026 10:54",
                "end": "03-03-2026 23:59",
                "name": "UNIT 8. Task - compulsory RA4, RA5"
            }
        },
        "tests": {
            "14076": {
                "type": "Cuestionario",
                "start": "",
                "end": "",
                "name": "UNIT 1. Quiz"
            },
            "14081": {
                "type": "Cuestionario",
                "start": "",
                "end": "",
                "name": "UNIT 2. Quiz"
            },
            "14086": {
                "type": "Cuestionario",
                "start": "",
                "end": "",
                "name": "UNIT 3. Quiz - compulsory"
            },
            "14091": {
                "type": "Cuestionario",
                "start": "",
                "end": "",
                "name": "UNIT 4. Quiz - compulsory"
            },
            "TE-DICIEMBRE": {
                "type": "Cuestionario",
                "start": "",
                "end": "",
                "name": "AUTOEVALUACIÓN DICIEMBRE"
            },
            "TE-ENERO_RA1": {
                "type": "Cuestionario",
                "start": "",
                "end": "",
                "name": "EXAMEN ENERO RA 1"
            },
            "TE-ENERO_RA2": {
                "type": "Cuestionario",
                "start": "",
                "end": "",
                "name": "EXAMEN ENERO RA 2"
            },
            "14095": {
                "type": "Cuestionario",
                "start": "",
                "end": "",
                "name": "UNIT 5. Quiz"
            },
            "14100": {
                "type": "Cuestionario",
                "start": "",
                "end": "",
                "name": "UNIT 6. Quiz"
            },
            "14104": {
                "type": "Cuestionario",
                "start": "",
                "end": "",
                "name": "UNIT 7. Quiz"
            },
            "14109": {
                "type": "Cuestionario",
                "start": "",
                "end": "",
                "name": "UNIT 8. Quiz"
            }
        },
        "notes": {
            "TE-doc": {
                "name": "Apuntes TE (doc)",
                "link": "https://docs.google.com/document/d/1sNMX-Q-9u_jSlT5Xy5Xyv47EAemb0U5YgsO0QxoG2SY/edit?usp=sharing"
            }
        }
    }
}